src/__init__.py
src/config.py
src/executor.py
src/main.py
src/selector.py
logo.txt
ai_selector-0.3.0.dist-info/METADATA
ai_selector-0.3.0.dist-info/WHEEL
ai_selector-0.3.0.dist-info/entry_points.txt
ai_selector-0.3.0.dist-info/licenses/LICENSE
ai_selector-0.3.0.dist-info/RECORD
