Metadata-Version: 2.4
Name: ai-selector
Version: 0.3.0
Summary: Interactive CLI tool for managing and executing multiple AI agents
Project-URL: Homepage, https://github.com/ramonpin/ai-selector
Project-URL: Repository, https://github.com/ramonpin/ai-selector.git
Project-URL: Issues, https://github.com/ramonpin/ai-selector/issues
Author-email: Ramñón Pin <ramon.pin@gmail.com>
License: MIT
License-File: LICENSE
Keywords: agent,ai,cli,interactive,selector,tool
Classifier: Development Status :: 3 - Alpha
Classifier: Environment :: Console
Classifier: Intended Audience :: Developers
Classifier: License :: OSI Approved :: MIT License
Classifier: Programming Language :: Python :: 3
Classifier: Programming Language :: Python :: 3.13
Classifier: Topic :: Software Development :: Libraries :: Application Frameworks
Classifier: Topic :: Utilities
Requires-Python: >=3.13
Requires-Dist: python-dotenv>=1.2.1
Requires-Dist: questionary>=2.1.1
